pycluster/__init__.py
pycluster/methods.py
teste_pycluster-1.0.0.dist-info/DESCRIPTION.rst
teste_pycluster-1.0.0.dist-info/METADATA
teste_pycluster-1.0.0.dist-info/RECORD
teste_pycluster-1.0.0.dist-info/WHEEL
teste_pycluster-1.0.0.dist-info/metadata.json
teste_pycluster-1.0.0.dist-info/top_level.txt
