Metadata-Version: 2.0
Name: teste-pycluster
Version: 1.0.0
Summary: This is a project test
Home-page: https://github.com/JaineBudke
Author: Jaine Budke
Author-email: jainebudke@hotmail.com
License: MIT
Keywords: bioinformatics neuroscience
Platform: UNKNOWN
Classifier: Development Status :: 1 - Planning
Classifier: Intended Audience :: Developers
Classifier: Topic :: Software Development :: Build Tools
Classifier: Intended Audience :: Science/Research
Classifier: Topic :: Scientific/Engineering :: Bio-Informatics
Classifier: License :: OSI Approved :: Academic Free License (AFL)
Classifier: Programming Language :: Python
Classifier: Programming Language :: Python :: 3
